elasticmon/__init__.py
elasticmon/client.py
elasticmon-1.2.0.dist-info/DESCRIPTION.rst
elasticmon-1.2.0.dist-info/METADATA
elasticmon-1.2.0.dist-info/RECORD
elasticmon-1.2.0.dist-info/WHEEL
elasticmon-1.2.0.dist-info/entry_points.txt
elasticmon-1.2.0.dist-info/metadata.json
elasticmon-1.2.0.dist-info/top_level.txt
